gzvoc/__init__py.py
gzvoc/gzvoc.py
gzvoc-0.0.3.dist-info/METADATA
gzvoc-0.0.3.dist-info/WHEEL
gzvoc-0.0.3.dist-info/top_level.txt
gzvoc-0.0.3.dist-info/RECORD
