Metadata-Version: 2.1
Name: gzvoc
Version: 0.0.3
Summary: 整理voc数据集
Home-page: https://weibo.com/xds95
Author: sxd
Author-email: sxd95@qq.com
License: UNKNOWN
Platform: any
Classifier: Programming Language :: Python :: 3
Classifier: License :: OSI Approved :: MIT License
Classifier: Operating System :: OS Independent
